freetshirts/CollegeEmails.csv
freetshirts/__init__.py
freetshirts/message.txt
freetshirts-0.31.dist-info/METADATA
freetshirts-0.31.dist-info/WHEEL
freetshirts-0.31.dist-info/top_level.txt
freetshirts-0.31.dist-info/RECORD
